{
  "baseUrl": "https://hakuya.top/after-the-rabbit-hole",
  "assets": [
    {
      "path": "assets/art/opening-rabbit-hole.jpg",
      "sha256": "a5ee5f0db74233e5924ca9780ef2cece6666628fd04583e1752be7648376d47f",
      "description": "Original opening illustration with the girl, white rabbit and rabbit hole"
    },
    {
      "path": "assets/art/dream-garden.jpg",
      "sha256": "a9286d857e68cf97a18ea9ebd0252f720caec82cfd228be08afcac8a825725fe",
      "description": "Original dream garden and maze background"
    },
    {
      "path": "assets/art/white-rabbit.png",
      "sha256": "1b186875ac746171bc55d1e91647b7535734f541f9fe889ce93ae2983caa9541",
      "description": "Original transparent white rabbit illustration"
    },
    {
      "path": "assets/art/alice-avatar.png",
      "sha256": "1e6be53d80156077f07136579f0d886bc6f753dbc237e1d9a80173142b7cb549",
      "description": "Original anime storybook heroine avatar based on the user's style reference"
    },
    {
      "path": "assets/art/teacup-portal.png",
      "sha256": "acf8f55f7005bc0be9a8b920926089d2c165137063657bb333d6aec3f5d1b8b0",
      "description": "Original watercolor enchanted teacup portal sprite"
    },
    {
      "path": "assets/art/card-guard.png",
      "sha256": "7719653a0714d9789a850fe0ae9859d774f960a1ade8ca9adbe3710f3dc30f0e",
      "description": "Original watercolor playing-card guard sprite"
    },
    {
      "path": "assets/art/pocket-watch.png",
      "sha256": "3077e9b14f8911f419a750f40cb96222da4aab426836f7527f9e43375bc6a78f",
      "description": "Original watercolor enchanted pocket-watch obstacle sprite"
    },
    {
      "path": "assets/art/mushroom-cluster.png",
      "sha256": "7837c2f3565d049695bca0993cd5e13d4a8b8cb9ab9c3e88775b824513be9af7",
      "description": "Original watercolor key-marked mushroom landmark sprite"
    },
    {
      "path": "assets/audio/rabbit-hole-bgm.mp3",
      "sha256": "07fbc52b04d3ba65e6753763a9e19326c332522a7f1ac1135a6bf367bcf6348a",
      "description": "BGM extracted from BV1ZK411B7cv, part 25, 不思議の国"
    }
  ]
}
